z3c/zcmlhook/__init__.py
z3c/zcmlhook/meta.zcml
z3c/zcmlhook/zcml.py
z3c/zcmlhook/tests/__init__.py
z3c/zcmlhook/tests/test1.zcml
z3c/zcmlhook/tests/test2.zcml
z3c/zcmlhook/tests/test3.zcml
z3c/zcmlhook/tests/test4.zcml
z3c/zcmlhook/tests/test_zcml.py
z3c_zcmlhook-3.0.dist-info/LICENSE.txt
z3c_zcmlhook-3.0.dist-info/METADATA
z3c_zcmlhook-3.0.dist-info/WHEEL
z3c_zcmlhook-3.0.dist-info/top_level.txt
z3c_zcmlhook-3.0.dist-info/RECORD
