Metadata-Version: 2.2
Name: z3c.zcmlhook
Version: 3.0
Summary: Easily hook into the ZCML processing machinery
Home-page: https://github.com/zopefoundation/z3c.zcmlhook
Author: Martin Aspeli
Author-email: zope-dev@zope.dev
License: ZPL
Keywords: zope zcml hook
Classifier: Development Status :: 6 - Mature
Classifier: Environment :: Web Environment
Classifier: Intended Audience :: Developers
Classifier: License :: OSI Approved :: Zope Public License
Classifier: Programming Language :: Python
Classifier: Programming Language :: Python :: 3
Classifier: Programming Language :: Python :: 3.9
Classifier: Programming Language :: Python :: 3.10
Classifier: Programming Language :: Python :: 3.11
Classifier: Programming Language :: Python :: 3.12
Classifier: Programming Language :: Python :: 3.13
Classifier: Topic :: Software Development :: Libraries :: Python Modules
Requires-Python: >=3.9
License-File: LICENSE.txt
Requires-Dist: setuptools
Requires-Dist: zope.component
Requires-Dist: zope.interface
Requires-Dist: zope.schema
Requires-Dist: zope.configuration
Provides-Extra: test
Requires-Dist: zope.component[test]; extra == "test"
Dynamic: author
Dynamic: author-email
Dynamic: classifier
Dynamic: description
Dynamic: home-page
Dynamic: keywords
Dynamic: license
Dynamic: provides-extra
Dynamic: requires-dist
Dynamic: requires-python
Dynamic: summary
